Workbook

Sheet DCF
A1: ="DCF - "&Datos!B1
A2: Cifras en miles de millones USD, salvo precios por acción. Todo se calcula solo: no escribas en esta hoja.
A3: Proyección del flujo de caja libre | C3: Año base
A4: Periodo | D4: 1 | E4: =D4+1 | F4: =E4+1 | G4: =F4+1 | H4: =G4+1 | I4: =H4+1 | J4: =I4+1 | K4: =J4+1 | L4: =K4+1 | M4: =L4+1
A5: Año fiscal | C5: =Datos!F5 | D5: =C5+1 | E5: =D5+1 | F5: =E5+1 | G5: =F5+1 | H5: =G5+1 | I5: =H5+1 | J5: =I5+1 | K5: =J5+1 | ... M5: =L5+1
A6: Ingresos | C6: =Datos!F6 | D6: =C6*(1+Supuestos!D22) | E6: =D6*(1+Supuestos!E22) | F6: =E6*(1+Supuestos!F22) | G6: =F6*(1+Supuestos!G22) | H6: =G6*(1+Supuestos!H22) | I6: =H6*(1+Supuestos!I22) | J6: =I6*(1+Supuestos!J22) | K6: =J6*(1+Supuestos!K22) | ... M6: =L6*(1+Supuestos!M22)
A7: CFO | C7: =Datos!F7 | D7: =D6*Supuestos!D23 | E7: =E6*Supuestos!E23 | F7: =F6*Supuestos!F23 | G7: =G6*Supuestos!G23 | H7: =H6*Supuestos!H23 | I7: =I6*Supuestos!I23 | J7: =J6*Supuestos!J23 | K7: =K6*Supuestos!K23 | ... M7: =M6*Supuestos!M23
A8: Capex + arrendamientos | C8: =Datos!F8+Datos!F9 | D8: =D6*Supuestos!D24 | E8: =E6*Supuestos!E24 | F8: =F6*Supuestos!F24 | G8: =G6*Supuestos!G24 | H8: =H6*Supuestos!H24 | I8: =I6*Supuestos!I24 | J8: =J6*Supuestos!J24 | K8: =K6*Supuestos!K24 | ... M8: =M6*Supuestos!M24
A9: SBC | C9: =Datos!F10 | D9: =D6*Supuestos!D25 | E9: =E6*Supuestos!E25 | F9: =F6*Supuestos!F25 | G9: =G6*Supuestos!G25 | H9: =H6*Supuestos!H25 | I9: =I6*Supuestos!I25 | J9: =J6*Supuestos!J25 | K9: =K6*Supuestos!K25 | ... M9: =M6*Supuestos!M25
A10: FCF - SBC | C10: =Datos!F16 | D10: =D7-D8-D9 | E10: =E7-E8-E9 | F10: =F7-F8-F9 | G10: =G7-G8-G9 | H10: =H7-H8-H9 | I10: =I7-I8-I9 | J10: =J7-J8-J9 | K10: =K7-K8-K9 | ... M10: =M7-M8-M9
A11: Factor de descuento | D11: =1/(1+Supuestos!$B$16)^D4 | E11: =1/(1+Supuestos!$B$16)^E4 | F11: =1/(1+Supuestos!$B$16)^F4 | G11: =1/(1+Supuestos!$B$16)^G4 | H11: =1/(1+Supuestos!$B$16)^H4 | I11: =1/(1+Supuestos!$B$16)^I4 | J11: =1/(1+Supuestos!$B$16)^J4 | K11: =1/(1+Supuestos!$B$16)^K4 | ... M11: =1/(1+Supuestos!$B$16)^M4
A12: Valor presente del FCF - SBC | D12: =D10*D11 | E12: =E10*E11 | F12: =F10*F11 | G12: =G10*G11 | H12: =H10*H11 | I12: =I10*I11 | J12: =J10*J11 | K12: =K10*K11 | ... M12: =M10*M11
A14: Valoración
A15: Suma del valor presente del FCF - SBC (años 1 a 10) | B15: =SUM(D12:M12)
A16: FCF - SBC del año 10 x (1 + g) | B16: =M10*(1+Supuestos!B17)
A17: Valor terminal = fila 16 / (WACC − g) | B17: =IF(Supuestos!B16<=Supuestos!B17,"WACC debe ser > g",B16/(Supuestos!B16-Supuestos!B17))
A18: Valor presente del valor terminal | B18: =B17*M11
A19: Valor de la empresa (EV) | B19: =B15+B18
A20: % del valor que viene del valor terminal | B20: =B18/B19 | C20: ← si supera 75%, el resultado es muy sensible al WACC y a g
A21: + Caja y valores negociables | B21: =Datos!F11+Datos!F12
A22: − Deuda | B22: =Datos!F13
A23: Valor del capital (equity) | B23: =B19+B21-B22
A24: Acciones diluidas (miles de millones) | B24: =Datos!F14
A25: Valor intrínseco por acción ($) | B25: =B23/B24
A26: Precio con margen de seguridad ($) | B26: =B25*(1-Supuestos!B18)
A27: Precio actual ($) | B27: =Supuestos!B6
A28: Valor intrínseco vs. precio actual | B28: =IF(B27>0,B25/B27-1,"sin precio")
A30: Sensibilidad del valor intrínseco por acción ($) — filas: WACC, columnas: crecimiento perpetuo g
A31: WACC \ g | B31: =Supuestos!$B$17+(-0.01) | C31: =Supuestos!$B$17+(-0.005) | D31: =Supuestos!$B$17+(0) | E31: =Supuestos!$B$17+(0.005) | F31: =Supuestos!$B$17+(0.01)
A32: =Supuestos!$B$16+(-0.02) | B32: =IF($A32<=B$31,"n/a",(SUMPRODUCT($D$10:$M$10/(1+$A32)^$D$4:$M$4)+$M$10*(1+B$31)/($A32-B$31)/(1+$A32)^10+$B$21-$B$22)/$B$24) | C32: =IF($A32<=C$31,"n/a",(SUMPRODUCT($D$10:$M$10/(1+$A32)^$D$4:$M$4)+$M$10*(1+C$31)/($A32-C$31)/(1+$A32)^10+$B$21-$B$22)/$B$24) | D32: =IF($A32<=D$31,"n/a",(SUMPRODUCT($D$10:$M$10/(1+$A32)^$D$4:$M$4)+$M$10*(1+D$31)/($A32-D$31)/(1+$A32)^10+$B$21-$B$22)/$B$24) | E32: =IF($A32<=E$31,"n/a",(SUMPRODUCT($D$10:$M$10/(1+$A32)^$D$4:$M$4)+$M$10*(1+E$31)/($A32-E$31)/(1+$A32)^10+$B$21-$B$22)/$B$24) | F32: =IF($A32<=F$31,"n/a",(SUMPRODUCT($D$10:$M$10/(1+$A32)^$D$4:$M$4)+$M$10*(1+F$31)/($A32-F$31)/(1+$A32)^10+$B$21-$B$22)/$B$24)
A33: =Supuestos!$B$16+(-0.01) | B33: =IF($A33<=B$31,"n/a",(SUMPRODUCT($D$10:$M$10/(1+$A33)^$D$4:$M$4)+$M$10*(1+B$31)/($A33-B$31)/(1+$A33)^10+$B$21-$B$22)/$B$24) | C33: =IF($A33<=C$31,"n/a",(SUMPRODUCT($D$10:$M$10/(1+$A33)^$D$4:$M$4)+$M$10*(1+C$31)/($A33-C$31)/(1+$A33)^10+$B$21-$B$22)/$B$24) | D33: =IF($A33<=D$31,"n/a",(SUMPRODUCT($D$10:$M$10/(1+$A33)^$D$4:$M$4)+$M$10*(1+D$31)/($A33-D$31)/(1+$A33)^10+$B$21-$B$22)/$B$24) | E33: =IF($A33<=E$31,"n/a",(SUMPRODUCT($D$10:$M$10/(1+$A33)^$D$4:$M$4)+$M$10*(1+E$31)/($A33-E$31)/(1+$A33)^10+$B$21-$B$22)/$B$24) | F33: =IF($A33<=F$31,"n/a",(SUMPRODUCT($D$10:$M$10/(1+$A33)^$D$4:$M$4)+$M$10*(1+F$31)/($A33-F$31)/(1+$A33)^10+$B$21-$B$22)/$B$24)
A34: =Supuestos!$B$16+(0) | B34: =IF($A34<=B$31,"n/a",(SUMPRODUCT($D$10:$M$10/(1+$A34)^$D$4:$M$4)+$M$10*(1+B$31)/($A34-B$31)/(1+$A34)^10+$B$21-$B$22)/$B$24) | C34: =IF($A34<=C$31,"n/a",(SUMPRODUCT($D$10:$M$10/(1+$A34)^$D$4:$M$4)+$M$10*(1+C$31)/($A34-C$31)/(1+$A34)^10+$B$21-$B$22)/$B$24) | D34: =IF($A34<=D$31,"n/a",(SUMPRODUCT($D$10:$M$10/(1+$A34)^$D$4:$M$4)+$M$10*(1+D$31)/($A34-D$31)/(1+$A34)^10+$B$21-$B$22)/$B$24) | E34: =IF($A34<=E$31,"n/a",(SUMPRODUCT($D$10:$M$10/(1+$A34)^$D$4:$M$4)+$M$10*(1+E$31)/($A34-E$31)/(1+$A34)^10+$B$21-$B$22)/$B$24) | F34: =IF($A34<=F$31,"n/a",(SUMPRODUCT($D$10:$M$10/(1+$A34)^$D$4:$M$4)+$M$10*(1+F$31)/($A34-F$31)/(1+$A34)^10+$B$21-$B$22)/$B$24)
A35: =Supuestos!$B$16+(0.01) | B35: =IF($A35<=B$31,"n/a",(SUMPRODUCT($D$10:$M$10/(1+$A35)^$D$4:$M$4)+$M$10*(1+B$31)/($A35-B$31)/(1+$A35)^10+$B$21-$B$22)/$B$24) | C35: =IF($A35<=C$31,"n/a",(SUMPRODUCT($D$10:$M$10/(1+$A35)^$D$4:$M$4)+$M$10*(1+C$31)/($A35-C$31)/(1+$A35)^10+$B$21-$B$22)/$B$24) | D35: =IF($A35<=D$31,"n/a",(SUMPRODUCT($D$10:$M$10/(1+$A35)^$D$4:$M$4)+$M$10*(1+D$31)/($A35-D$31)/(1+$A35)^10+$B$21-$B$22)/$B$24) | E35: =IF($A35<=E$31,"n/a",(SUMPRODUCT($D$10:$M$10/(1+$A35)^$D$4:$M$4)+$M$10*(1+E$31)/($A35-E$31)/(1+$A35)^10+$B$21-$B$22)/$B$24) | F35: =IF($A35<=F$31,"n/a",(SUMPRODUCT($D$10:$M$10/(1+$A35)^$D$4:$M$4)+$M$10*(1+F$31)/($A35-F$31)/(1+$A35)^10+$B$21-$B$22)/$B$24)
A36: =Supuestos!$B$16+(0.02) | B36: =IF($A36<=B$31,"n/a",(SUMPRODUCT($D$10:$M$10/(1+$A36)^$D$4:$M$4)+$M$10*(1+B$31)/($A36-B$31)/(1+$A36)^10+$B$21-$B$22)/$B$24) | C36: =IF($A36<=C$31,"n/a",(SUMPRODUCT($D$10:$M$10/(1+$A36)^$D$4:$M$4)+$M$10*(1+C$31)/($A36-C$31)/(1+$A36)^10+$B$21-$B$22)/$B$24) | D36: =IF($A36<=D$31,"n/a",(SUMPRODUCT($D$10:$M$10/(1+$A36)^$D$4:$M$4)+$M$10*(1+D$31)/($A36-D$31)/(1+$A36)^10+$B$21-$B$22)/$B$24) | E36: =IF($A36<=E$31,"n/a",(SUMPRODUCT($D$10:$M$10/(1+$A36)^$D$4:$M$4)+$M$10*(1+E$31)/($A36-E$31)/(1+$A36)^10+$B$21-$B$22)/$B$24) | F36: =IF($A36<=F$31,"n/a",(SUMPRODUCT($D$10:$M$10/(1+$A36)^$D$4:$M$4)+$M$10*(1+F$31)/($A36-F$31)/(1+$A36)^10+$B$21-$B$22)/$B$24)

Sheet Supuestos
A1: Supuestos del DCF
A2: Celdas AMARILLAS = tus supuestos (edítalas). Negro = fórmulas. Verde = datos que vienen de la hoja Datos.
A3: Los valores amarillos que vienen en la plantilla son EJEMPLOS genéricos: reemplázalos antes de sacar conclusiones.
A5: Mercado y tasa de descuento
A6: Precio actual de la acción ($) | C6: ← lo rellena la app con el precio del día de descarga
A7: Tasa libre de riesgo (bono del Tesoro 10 años) | B7: 0.045
A8: Beta | B8: 1.2
A9: Prima de riesgo de mercado | B9: 0.05
A10: Costo del capital (Ke = Rf + Beta x Prima) | B10: =B7+B8*B9
A11: Costo de la deuda antes de impuestos | B11: 0.05
A12: Tasa de impuestos | B12: 0.21
A13: Capitalización de mercado ($ miles de millones) | B13: =B6*Datos!F14
A14: Deuda ($ miles de millones) | B14: =Datos!F13
A15: Peso del capital propio E / (E + D) | B15: =IF(B13+B14>0,B13/(B13+B14),1)
A16: WACC = peso x Ke + (1 − peso) x Kd x (1 − impuestos) | B16: =B15*B10+(1-B15)*B11*(1-B12)
A17: Crecimiento perpetuo (g) | B17: 0.025
A18: Margen de seguridad | B18: 0.2
A20: Proyección a 10 años (todo como % de ingresos)
A21: Concepto (columnas D-M = año 1 a 10 de la proyección) | B21: Último año | C21: Promedio hist. | D21: 1 | E21: 2 | F21: 3 | G21: 4 | H21: 5 | I21: 6 | J21: 7 | K21: 8 | L21: 9 | M21: 10
A22: Crecimiento de ingresos | B22: =Datos!F6/Datos!E6-1 | C22: =(Datos!F6/Datos!B6)^(1/4)-1 | D22: 0.12 | E22: =$D22+($M22-$D22)*(E$21-1)/9 | F22: =$D22+($M22-$D22)*(F$21-1)/9 | G22: =$D22+($M22-$D22)*(G$21-1)/9 | H22: =$D22+($M22-$D22)*(H$21-1)/9 | I22: =$D22+($M22-$D22)*(I$21-1)/9 | J22: =$D22+($M22-$D22)*(J$21-1)/9 | K22: =$D22+($M22-$D22)*(K$21-1)/9 | L22: =$D22+($M22-$D22)*(L$21-1)/9 | M22: 0.04
A23: CFO como % de ingresos | B23: =Datos!F7/Datos!F6 | C23: =AVERAGE(Datos!D7/Datos!D6,Datos!E7/Datos!E6,Datos!F7/Datos!F6) | D23: =ROUND(C23,3) | E23: =$D23 | F23: =$D23 | G23: =$D23 | H23: =$D23 | I23: =$D23 | J23: =$D23 | K23: =$D23 | L23: =$D23 | M23: =$D23
A24: Capex + arrendamientos como % de ingresos | B24: =(Datos!F8+Datos!F9)/Datos!F6 | C24: =AVERAGE((Datos!B8+Datos!B9)/Datos!B6,(Datos!C8+Datos!C9)/Datos!C6,(Datos!D8+Datos!D9)/Datos!D6,(Datos!E8+Datos!E9)/Datos!E6) | D24: =ROUND(B24,3) | E24: =IF(E$21>=$B$26,$M24,$D24+($M24-$D24)*(E$21-1)/($B$26-1)) | F24: =IF(F$21>=$B$26,$M24,$D24+($M24-$D24)*(F$21-1)/($B$26-1)) | G24: =IF(G$21>=$B$26,$M24,$D24+($M24-$D24)*(G$21-1)/($B$26-1)) | H24: =IF(H$21>=$B$26,$M24,$D24+($M24-$D24)*(H$21-1)/($B$26-1)) | I24: =IF(I$21>=$B$26,$M24,$D24+($M24-$D24)*(I$21-1)/($B$26-1)) | J24: =IF(J$21>=$B$26,$M24,$D24+($M24-$D24)*(J$21-1)/($B$26-1)) | K24: =IF(K$21>=$B$26,$M24,$D24+($M24-$D24)*(K$21-1)/($B$26-1)) | L24: =IF(L$21>=$B$26,$M24,$D24+($M24-$D24)*(L$21-1)/($B$26-1)) | M24: =ROUND(C24,3)
A25: SBC como % de ingresos | B25: =Datos!F10/Datos!F6 | C25: =AVERAGE(Datos!D10/Datos!D6,Datos!E10/Datos!E6,Datos!F10/Datos!F6) | D25: =ROUND(B25,3) | E25: =$D25 | F25: =$D25 | G25: =$D25 | H25: =$D25 | I25: =$D25 | J25: =$D25 | K25: =$D25 | L25: =$D25 | M25: =$D25
A26: Año en que el capex llega al nivel normal (columna M) | B26: 5
A27: Ejemplos: crecimiento 12% → 4% lineal; CFO = promedio 3 años; capex baja del último año al promedio de los 4 años previos; SBC = último año. 'Promedio hist.' es de 3 años, salvo capex (4 años previos al último).

Sheet Datos
A1: Ticker
A2: Actualizado
A3: Fuente | B3: SEC EDGAR, API companyfacts (reportes 10-K). Hoja escrita por extraer_datos.py: no editar a mano.
A5: Concepto (miles de millones USD)
A6: Ingresos
A7: CFO (flujo operativo)
A8: Capex
A9: Arrendamientos financieros
A10: SBC (compensación en acciones)
A11: Caja
A12: Valores negociables
A13: Deuda
A14: Acciones diluidas (miles de millones)
A15: FCF (CFO − capex − arrendamientos) | B15: =B7-B8-B9 | C15: =C7-C8-C9 | D15: =D7-D8-D9 | E15: =E7-E8-E9 | F15: =F7-F8-F9
A16: FCF − SBC | B16: =B15-B10 | C16: =C15-C10 | D16: =D15-D10 | E16: =E15-E10 | F16: =F15-F10
